<?xml version="1.0" encoding="utf-8" ?>
<config>
	<url target="_top">/about/fashion_blog/</url>
	<overlay>/images/blog/banner/pic_overlay.png</overlay>
	
	<slides>
		<slide>
			<image>/images/blog/banner/pic2.jpg</image>
			<point x="0" y="-200" time="0" />
			<point x="-90" y="0" time="1200" />
			<point x="30" y="-100" time="1200" />
			<point x="10" y="300" time="1800" />
		</slide>
		<slide>
			<image>/images/blog/banner/pic1.jpg</image>
			<point x="0" y="-300" time="0" />
			<point x="-101" y="70" time="1200" />
			<point x="60" y="100" time="1200" />
			<point x="-30" y="130" time="1800" />
			<point x="0" y="0" time="300" />
		</slide>
		<slide>
			<image>/images/blog/banner/pic3.jpg</image>
			<point x="-121" y="0" time="0" />
			<point x="100" y="-150" time="1200" />
			<point x="-100" y="-150" time="1200" />
			<point x="60" y="300" time="1800" />
		</slide>
	</slides>
</config>